st_error_boundary/__init__.py
st_error_boundary/error_boundary.py
st_error_boundary/py.typed
st_error_boundary/plugins/__init__.py
st_error_boundary-0.1.8.dist-info/METADATA
st_error_boundary-0.1.8.dist-info/WHEEL
st_error_boundary-0.1.8.dist-info/RECORD
