Metadata-Version: 2.4
Name: st-error-boundary
Version: 0.1.8
Summary: A tiny, typed error-boundary decorator for Streamlit apps (UI-safe fallback + pluggable hooks)
Project-URL: Homepage, https://github.com/K-dash/st-error-boundary
Project-URL: Repository, https://github.com/K-dash/st-error-boundary
Author: K-dash
License: MIT
Keywords: decorator,error-boundary,error-handling,streamlit
Classifier: Development Status :: 4 - Beta
Classifier: Intended Audience :: Developers
Classifier: License :: OSI Approved :: MIT License
Classifier: Programming Language :: Python :: 3.12
Classifier: Programming Language :: Python :: 3.13
Classifier: Topic :: Software Development :: Libraries :: Python Modules
Classifier: Typing :: Typed
Requires-Python: >=3.12
Requires-Dist: streamlit>=1.50
